MANIFEST.in
README.txt
setup.py
docs/HISTORY.txt
docs/INSTALL.txt
docs/LICENSE.GPL
docs/LICENSE.txt
redomino/__init__.py
redomino.contentwellportlets.egg-info/PKG-INFO
redomino.contentwellportlets.egg-info/SOURCES.txt
redomino.contentwellportlets.egg-info/dependency_links.txt
redomino.contentwellportlets.egg-info/entry_points.txt
redomino.contentwellportlets.egg-info/namespace_packages.txt
redomino.contentwellportlets.egg-info/not-zip-safe
redomino.contentwellportlets.egg-info/requires.txt
redomino.contentwellportlets.egg-info/top_level.txt
redomino/contentwellportlets/__init__.py
redomino/contentwellportlets/configure.zcml
redomino/contentwellportlets/migrations.py
redomino/contentwellportlets/upgrades.zcml
redomino/contentwellportlets/browser/__init__.py
redomino/contentwellportlets/browser/configure.zcml
redomino/contentwellportlets/browser/interfaces.py
redomino/contentwellportlets/browser/manager.py
redomino/contentwellportlets/browser/viewlets.py
redomino/contentwellportlets/browser/styles/ContentWellPortlets.css
redomino/contentwellportlets/browser/templates/footerportlets.pt
redomino/contentwellportlets/browser/templates/inheaderportlets.pt
redomino/contentwellportlets/browser/templates/managefooterportlets.pt
redomino/contentwellportlets/browser/templates/manageinheaderportlets.pt
redomino/contentwellportlets/browser/templates/manageportletsabove.pt
redomino/contentwellportlets/browser/templates/manageportletsbelow.pt
redomino/contentwellportlets/browser/templates/manageportletsbelowtitle.pt
redomino/contentwellportlets/browser/templates/portletsabovecontent.pt
redomino/contentwellportlets/browser/templates/portletsbelowcontent.pt
redomino/contentwellportlets/browser/templates/portletsbelowcontenttitle.pt
redomino/contentwellportlets/browser/templates/renderer.pt
redomino/contentwellportlets/i18n/contentwellportlets-it.po
redomino/contentwellportlets/i18n/redomino.contentwellportlets-es.po
redomino/contentwellportlets/i18n/redomino.contentwellportlets-fr.po
redomino/contentwellportlets/i18n/redomino.contentwellportlets-it.po
redomino/contentwellportlets/i18n/redomino.contentwellportlets-manual.pot
redomino/contentwellportlets/i18n/redomino.contentwellportlets.pot
redomino/contentwellportlets/locales/rebuild_i18n.sh
redomino/contentwellportlets/locales/redomino.contentwellportlets-manual.pot
redomino/contentwellportlets/locales/redomino.contentwellportlets.pot
