Metadata-Version: 1.0
Name: redomino.contentwellportlets
Version: 4.1.2
Summary: A Plone product that enables you to add portlets to the central column in a page
Home-page: https://github.com/redomino/redomino.contentwellportlets
Author: Redomino
Author-email: info@redomino.com
License: GPL
Keywords: plone portletmanager
Platform: UNKNOWN
Classifier: Framework :: Plone
Classifier: Programming Language :: Python
Classifier: Topic :: Software Development :: Libraries :: Python Modules
